shellyapi/__init__.py
shellyapi/shellyapi.py
shellyapi/validations.py
tests/__init__.py
tests/test_shellyapi.py
tests/test_validations.py
shelly_cloud-0.2.0.dist-info/LICENSE
shelly_cloud-0.2.0.dist-info/METADATA
shelly_cloud-0.2.0.dist-info/WHEEL
shelly_cloud-0.2.0.dist-info/top_level.txt
shelly_cloud-0.2.0.dist-info/RECORD
