Metadata-Version: 2.1
Name: shelly-cloud
Version: 0.2.0
Summary: A Python API for accessing the Shelly devices.
Home-page: 
Author: 
Author-email: Ingmar Mueller <ingmar.mueller@kfw.de>, Mario Macai <mario.macai@accenture.com>, Melissa Schmidt <melissa.schmidt@accenture.com>, Georgia Moldovan <georgia.moldovan@accenture.com>, Felix Stark <felix.stark@kfw.de>
Project-URL: Bug Tracker, https://github.com/openkfw/shelly-cloud/issues
Project-URL: Homepage, https://github.com/openkfw/shelly-cloud
Keywords: shelly,kfw,api,cloud
Classifier: Programming Language :: Python :: 3
Classifier: License :: OSI Approved :: MIT License
Classifier: Operating System :: OS Independent
Provides: shellyapi
Requires-Python: >=3.7
License-File: LICENSE
Requires-Dist: requests (>=2.27.1)
Provides-Extra: dev
Requires-Dist: black ; extra == 'dev'
Requires-Dist: pytest ; extra == 'dev'
Requires-Dist: python-dotenv ; extra == 'dev'
Requires-Dist: pre-commit ; extra == 'dev'
